jupyterlab_filebrowser_terminal/__init__.py
jupyterlab_filebrowser_terminal/_version.py
jupyterlab_filebrowser_terminal/labextension/build_log.json
jupyterlab_filebrowser_terminal/labextension/package.json
jupyterlab_filebrowser_terminal/labextension/schemas/jupyterlab-filebrowser-terminal/package.json.orig
jupyterlab_filebrowser_terminal/labextension/schemas/jupyterlab-filebrowser-terminal/plugin.json
jupyterlab_filebrowser_terminal/labextension/static/lib_index_js.0f1953677290e8920561.js
jupyterlab_filebrowser_terminal/labextension/static/lib_index_js.0f1953677290e8920561.js.map
jupyterlab_filebrowser_terminal/labextension/static/lib_index_js.196b8fe00b3fbb78e7ef.js
jupyterlab_filebrowser_terminal/labextension/static/lib_index_js.196b8fe00b3fbb78e7ef.js.map
jupyterlab_filebrowser_terminal/labextension/static/lib_index_js.1b42c1afab3e7bc73583.js
jupyterlab_filebrowser_terminal/labextension/static/lib_index_js.1b42c1afab3e7bc73583.js.map
jupyterlab_filebrowser_terminal/labextension/static/lib_index_js.21b56ea10d4e59a7b69f.js
jupyterlab_filebrowser_terminal/labextension/static/lib_index_js.21b56ea10d4e59a7b69f.js.map
jupyterlab_filebrowser_terminal/labextension/static/lib_index_js.24e85cae791f3721dfb4.js
jupyterlab_filebrowser_terminal/labextension/static/lib_index_js.24e85cae791f3721dfb4.js.map
jupyterlab_filebrowser_terminal/labextension/static/lib_index_js.25e33e52c9e550d86191.js
jupyterlab_filebrowser_terminal/labextension/static/lib_index_js.25e33e52c9e550d86191.js.map
jupyterlab_filebrowser_terminal/labextension/static/lib_index_js.3dead9344fc08a5d76a5.js
jupyterlab_filebrowser_terminal/labextension/static/lib_index_js.3dead9344fc08a5d76a5.js.map
jupyterlab_filebrowser_terminal/labextension/static/lib_index_js.625920e49b31ff1eb0c3.js
jupyterlab_filebrowser_terminal/labextension/static/lib_index_js.625920e49b31ff1eb0c3.js.map
jupyterlab_filebrowser_terminal/labextension/static/lib_index_js.6712b20604a1608fba5a.js
jupyterlab_filebrowser_terminal-0.1.0.dist-info/LICENSE
jupyterlab_filebrowser_terminal-0.1.0.dist-info/METADATA
jupyterlab_filebrowser_terminal-0.1.0.dist-info/WHEEL
jupyterlab_filebrowser_terminal-0.1.0.dist-info/top_level.txt
jupyterlab_filebrowser_terminal-0.1.0.dist-info/RECORD
