Metadata-Version: 2.1
Name: jupyterlab-filebrowser-terminal
Version: 0.1.0
Summary: A simple extension to open a JupyterLab terminal in the current filebrowser location
Home-page: https://github.com/agooes77/jupyterlab-filebrowser-terminal
Author: Angus Hollands
Author-email: goosey15@gmail.com
License: BSD-3-Clause
Keywords: Jupyter,JupyterLab,JupyterLab3
Platform: Linux
Platform: Mac OS X
Platform: Windows
Classifier: License :: OSI Approved :: BSD License
Classifier: Programming Language :: Python
Classifier: Programming Language :: Python :: 3
Classifier: Programming Language :: Python :: 3.6
Classifier: Programming Language :: Python :: 3.7
Classifier: Programming Language :: Python :: 3.8
Classifier: Programming Language :: Python :: 3.9
Classifier: Framework :: Jupyter
Requires-Python: >=3.6
License-File: LICENSE
